iemap/__init__.py
iemap/functions.py
iemap/helpers.py
iemap/models.py
iemap-0.4.0.dist-info/LICENSE
iemap-0.4.0.dist-info/METADATA
iemap-0.4.0.dist-info/WHEEL
iemap-0.4.0.dist-info/top_level.txt
iemap-0.4.0.dist-info/RECORD
