Metadata-Version: 2.1
Name: iemap
Version: 0.4.0
Summary: Tools to use IEMAP Rest API
Author-email: Sergio Ferlito <sergio.ferlito@enea.it>, Marco Puccini <marco.puccini@enea.it>
Maintainer-email: Marco Puccini <marco.puccini@enea.it>
Project-URL: Homepage, https://github.com/ai4mat/iemap-module
Project-URL: Bug Tracker, https://github.com/ai4mat/iemap-module/issues
Classifier: Development Status :: 5 - Production/Stable
Classifier: Intended Audience :: Science/Research
Classifier: Operating System :: OS Independent
Classifier: Topic :: Scientific/Engineering
Classifier: Topic :: Software Development :: Libraries :: Python Modules
Classifier: License :: OSI Approved :: GNU General Public License (GPL)
Classifier: Programming Language :: Python
Classifier: Programming Language :: Python :: 3
Classifier: Programming Language :: Python :: 3 :: Only
Classifier: Programming Language :: Python :: 3.9
Classifier: Programming Language :: Python :: 3.10
Classifier: Topic :: Scientific/Engineering :: Physics
Classifier: Topic :: Utilities
Requires-Python: >=3.9
License-File: LICENSE
Requires-Dist: requests (==2.28.1)
Requires-Dist: requests-toolbelt (==0.9.1)
Requires-Dist: bson (==0.5.10)
Requires-Dist: pydantic (==1.10.2)
